drf_serpy/__init__.py
drf_serpy/fields.py
drf_serpy/serializer.py
drf_serpy-0.5.0.dist-info/LICENSE
drf_serpy-0.5.0.dist-info/METADATA
drf_serpy-0.5.0.dist-info/WHEEL
drf_serpy-0.5.0.dist-info/RECORD
