Metadata-Version: 2.1
Name: drf-serpy
Version: 0.5.0
Summary: Ridiculously fast object serialization
License: MIT
Keywords: serialization,rest,json,api,marshal,marshalling,validation,schema,fast
Author: Sergen Pekşen
Author-email: speksen@kb01.ai
Requires-Python: >=3.6,<4.0
Classifier: Development Status :: 4 - Beta
Classifier: Intended Audience :: Developers
Classifier: License :: OSI Approved :: MIT License
Classifier: Programming Language :: Python :: 3
Classifier: Programming Language :: Python :: 3.6
Classifier: Programming Language :: Python :: 3.7
Classifier: Programming Language :: Python :: 3.8
Classifier: Programming Language :: Python :: 3.9
Classifier: Programming Language :: Python :: 3.10
Classifier: Programming Language :: Python :: 3.11
Classifier: Programming Language :: Python :: 3.12
Classifier: Programming Language :: Python :: Implementation :: CPython
Classifier: Programming Language :: Python :: Implementation :: PyPy
Requires-Dist: drf-yasg (>=1.20.0,<2.0.0)
